oasm/rtmq2/__init__.py
oasm/rtmq2/intf.py
oasm/rtmq2/wasm.py
oasm_rtmq2-0.1.11.dist-info/METADATA
oasm_rtmq2-0.1.11.dist-info/WHEEL
oasm_rtmq2-0.1.11.dist-info/top_level.txt
oasm_rtmq2-0.1.11.dist-info/RECORD
